my_eda_helper/__init__.py
my_eda_helper/core.py
my_eda_helper-0.1.2.dist-info/LICENSE
my_eda_helper-0.1.2.dist-info/METADATA
my_eda_helper-0.1.2.dist-info/WHEEL
my_eda_helper-0.1.2.dist-info/top_level.txt
my_eda_helper-0.1.2.dist-info/RECORD
